wagtailcodeblock/__init__.py
wagtailcodeblock/_version.py
wagtailcodeblock/blocks.py
wagtailcodeblock/settings.py
wagtailcodeblock/wagtail_hooks.py
wagtailcodeblock/static/wagtailcodeblock/css/wagtail-code-block.css
wagtailcodeblock/static/wagtailcodeblock/css/wagtail-code-block.min.css
wagtailcodeblock/static/wagtailcodeblock/js/wagtailcodeblock.js
wagtailcodeblock/templates/wagtailcodeblock/code_block.html
wagtailcodeblock/templates/wagtailcodeblock/code_block_form.html
wagtailcodeblock/templates/wagtailcodeblock/raw_code.html
wagtailcodeblock/templatetags/__init__.py
wagtailcodeblock/templatetags/wagtailcodeblock_tags.py
wagtailcodeblock-1.29.0.2.dist-info/LICENSE
wagtailcodeblock-1.29.0.2.dist-info/METADATA
wagtailcodeblock-1.29.0.2.dist-info/WHEEL
wagtailcodeblock-1.29.0.2.dist-info/top_level.txt
wagtailcodeblock-1.29.0.2.dist-info/RECORD
