Metadata-Version: 2.1
Name: wagtailcodeblock
Version: 1.29.0.2
Summary: Wagtail Code Block provides PrismJS syntax highlighting in Wagtail.
Author-email: Tim Allen <tallen@wharton.upenn.edu>
License: BSD-3-Clause
Project-URL: Homepage, https://github.com/FlipperPA/wagtailcodeblock
Project-URL: Repository, https://github.com/FlipperPA/wagtailcodeblock
Project-URL: Documentation, https://github.com/FlipperPA/wagtailcodeblock
Keywords: wagtail,cms,contact,syntax,code,highlighting,highlighter
Classifier: Development Status :: 5 - Production/Stable
Classifier: Environment :: Web Environment
Classifier: Intended Audience :: Developers
Classifier: License :: OSI Approved :: BSD License
Classifier: Operating System :: OS Independent
Classifier: Programming Language :: Python :: 3
Classifier: Programming Language :: Python :: 3.8
Classifier: Programming Language :: Python :: 3.9
Classifier: Programming Language :: Python :: 3.10
Classifier: Programming Language :: Python :: 3.11
Classifier: Programming Language :: Python :: 3.12
Classifier: Framework :: Django
Classifier: Framework :: Wagtail
Classifier: Framework :: Wagtail :: 3
Classifier: Framework :: Wagtail :: 4
Classifier: Framework :: Wagtail :: 5
Classifier: Framework :: Wagtail :: 6
Classifier: Topic :: Internet :: WWW/HTTP
Classifier: Topic :: Internet :: WWW/HTTP :: Dynamic Content
Requires-Python: >=3.7
License-File: LICENSE
Requires-Dist: wagtail>=4
